ganbase/__init__.py
ganbase/version.py
ganbase/datasets/__init__.py
ganbase/evaluation/__init__.py
ganbase/evaluation/inceptionscore.py
ganbase/models/__init__.py
ganbase/models/dcgan.py
ganbase/models/mlp.py
ganbase/utils/__init__.py
ganbase/utils/timer.py
ganbase/visualize/__init__.py
ganbase/visualize/plots.py
ganbase-0.0.1.dist-info/DESCRIPTION.rst
ganbase-0.0.1.dist-info/METADATA
ganbase-0.0.1.dist-info/RECORD
ganbase-0.0.1.dist-info/WHEEL
ganbase-0.0.1.dist-info/metadata.json
ganbase-0.0.1.dist-info/top_level.txt
tests/__init__.py
tests/test_models.py
tests/test_preparation.py
